waveql/__init__.py
waveql/ai.py
waveql/async_connection.py
waveql/async_cursor.py
waveql/cache.py
waveql/chunked_executor.py
waveql/cli.py
waveql/config.py
waveql/connection.py
waveql/connection_base.py
waveql/cursor.py
waveql/exceptions.py
waveql/join_optimizer.py
waveql/observability.py
waveql/optimizer.py
waveql/py.typed
waveql/query_planner.py
waveql/resource_optimizer.py
waveql/schema_cache.py
waveql/streaming.py
waveql/webhooks.py
waveql/adapters/__init__.py
waveql/adapters/base.py
waveql/adapters/cloud_storage.py
waveql/adapters/file_adapter.py
waveql/adapters/google_sheets.py
waveql/adapters/hubspot.py
waveql/adapters/jira.py
waveql/adapters/registry.py
waveql/adapters/rest_adapter.py
waveql/adapters/salesforce.py
waveql/adapters/servicenow.py
waveql/adapters/shopify.py
waveql/adapters/singer.py
waveql/adapters/sql.py
waveql/adapters/stripe.py
waveql/adapters/zendesk.py
waveql/auth/__init__.py
waveql/auth/manager.py
waveql/cdc/__init__.py
waveql/cdc/models.py
waveql/cdc/postgres.py
waveql/cdc/providers.py
waveql/cdc/state.py
waveql/cdc/stream.py
waveql/contracts/__init__.py
waveql/contracts/models.py
waveql/contracts/registry.py
waveql/contracts/validator.py
waveql/materialized_view/__init__.py
waveql/materialized_view/manager.py
waveql/materialized_view/models.py
waveql/materialized_view/registry.py
waveql/materialized_view/storage.py
waveql/materialized_view/sync.py
waveql/pg_wire/__init__.py
waveql/pg_wire/catalog.py
waveql/pg_wire/cli.py
waveql/pg_wire/protocol.py
waveql/pg_wire/server.py
waveql/pg_wire/type_mapping.py
waveql/provenance/__init__.py
waveql/provenance/models.py
waveql/provenance/traced_adapter.py
waveql/provenance/tracker.py
waveql/security/__init__.py
waveql/security/policy.py
waveql/semantic/__init__.py
waveql/semantic/dbt.py
waveql/semantic/saved_queries.py
waveql/semantic/views.py
waveql/sqlalchemy/__init__.py
waveql/sqlalchemy/dialect.py
waveql/transaction/__init__.py
waveql/transaction/coordinator.py
waveql/utils/__init__.py
waveql-0.1.8.dist-info/METADATA
waveql-0.1.8.dist-info/WHEEL
waveql-0.1.8.dist-info/entry_points.txt
waveql-0.1.8.dist-info/licenses/LICENSE
waveql-0.1.8.dist-info/RECORD
