Metadata-Version: 2.4
Name: waveql
Version: 0.1.8
Summary: Universal Python connector for APIs - Query any data source with SQL
Project-URL: Homepage, https://github.com/mitayan0/WaveQL
Project-URL: Documentation, https://github.com/mitayan0/WaveQL/blob/main/docs/index.md
Project-URL: Repository, https://github.com/mitayan0/WaveQL
Author-email: Mitayan Chakma <mitayanchangma@gmail.com>
License-Expression: MIT
License-File: LICENSE
Keywords: api,connector,database,duckdb,postgres,salesforce,servicenow,sql
Classifier: Development Status :: 3 - Alpha
Classifier: Intended Audience :: Developers
Classifier: License :: OSI Approved :: MIT License
Classifier: Programming Language :: Python :: 3
Classifier: Programming Language :: Python :: 3.9
Classifier: Programming Language :: Python :: 3.10
Classifier: Programming Language :: Python :: 3.11
Classifier: Programming Language :: Python :: 3.12
Classifier: Topic :: Database
Requires-Python: >=3.9
Requires-Dist: anyio>=4.0
Requires-Dist: authlib>=1.3
Requires-Dist: duckdb>=1.0
Requires-Dist: httpx>=0.27
Requires-Dist: pandas>=2.0
Requires-Dist: pyarrow>=15.0
Requires-Dist: pydantic>=2.0
Requires-Dist: requests>=2.31
Requires-Dist: sqlalchemy>=2.0
Requires-Dist: sqlglot>=23.0
Provides-Extra: dev
Requires-Dist: black; extra == 'dev'
Requires-Dist: pytest-asyncio; extra == 'dev'
Requires-Dist: pytest-cov; extra == 'dev'
Requires-Dist: pytest>=7.0; extra == 'dev'
Requires-Dist: responses; extra == 'dev'
Requires-Dist: respx; extra == 'dev'
Requires-Dist: ruff; extra == 'dev'
Provides-Extra: postgres
Requires-Dist: psycopg2-binary>=2.9; extra == 'postgres'
